Metadata-Version: 2.1
Name: sqlalchemy-qubole
Version: 1.0.0
Summary: Qubole Presto/Hive for SQLAlchemy
Home-page: https://docs.qubole.com/en/latest/connectivity-options/partner-integration/sqlalchemy/sqlalchemy-index.html
Author: Qubole
Author-email: support@qubole.com
License: Apache License, Version 2.0
Keywords: SQLAlchemy Qubole
Platform: UNKNOWN
Classifier: Development Status :: 4 - Beta
Classifier: Environment :: Console
Classifier: Intended Audience :: Developers
Classifier: License :: OSI Approved :: Apache Software License
Classifier: Operating System :: OS Independent
Classifier: Programming Language :: Python
Classifier: Programming Language :: Python :: 3
Classifier: Programming Language :: Python :: Implementation :: CPython
Classifier: Topic :: Database :: Front-Ends
Provides-Extra: jdbc
